Metadata-Version: 2.1
Name: blatex
Version: 0.1.3
Summary: Simple cli tool for managing latex projects.
Home-page: https://github.com/BalderHolst/blatex
Author: Balder Holst
Author-email: balderwh@gmail.com
License: MIT
Requires-Python: >=3.7
License-File: LICENCE
